wagtailaltgenerator/__init__.py
wagtailaltgenerator/apps.py
wagtailaltgenerator/helpers.py
wagtailaltgenerator/signals.py
wagtailaltgenerator-1.0.0.dist-info/DESCRIPTION.rst
wagtailaltgenerator-1.0.0.dist-info/METADATA
wagtailaltgenerator-1.0.0.dist-info/RECORD
wagtailaltgenerator-1.0.0.dist-info/WHEEL
wagtailaltgenerator-1.0.0.dist-info/metadata.json
wagtailaltgenerator-1.0.0.dist-info/top_level.txt
