Metadata-Version: 2.0
Name: wagtailaltgenerator
Version: 1.0.0
Summary: Autogenerate image descriptions with the help of computer vision
Home-page: https://github.com/marteinn/wagtail-alt-generator
Author: marteinn
Author-email: martin@marteinn.se
License: MIT
Platform: UNKNOWN
Classifier: Development Status :: 3 - Alpha
Classifier: Environment :: Web Environment
Classifier: Intended Audience :: Developers
Classifier: Natural Language :: English
Classifier: Intended Audience :: Developers
Classifier: License :: OSI Approved :: MIT License
Classifier: Programming Language :: Python
Classifier: Programming Language :: Python :: 2
Classifier: Programming Language :: Python :: 2.7
Classifier: Framework :: Django
Classifier: Topic :: Utilities
Requires-Dist: requests
Requires-Dist: wagtail (>=1.7)
